{
    "name": "week5",
    "children": [
        {
            "name": "Outline",
            "children": [
                {
                    "name": "VLAN"
                }
            ]
        },
        {
            "name": "VLAN Aims and Benefits",
            "children": [
                {
                    "name": "group",
                    "children": [
                        {
                            "name": "VLAN"
                        }
                    ]
                }
            ]
        },
        {
            "name": "Virtual LANs Technologies",
            "children": [
                {
                    "name": "VLAN"
                }
            ]
        },
        {
            "name": "Port-based Virtual LANs",
            "children": [
                {
                    "name": "bridge/switch"
                }
            ]
        },
        {
            "name": "MAC-based Virtual LANs",
            "children": [
                {
                    "name": "bridge/switch"
                }
            ]
        },
        {
            "name": "MAC-based Virtual LANs -- MAC5 moves",
            "children": [
                {
                    "name": "bridge/switch"
                }
            ]
        },
        {
            "name": "IP Subnet-based Virtual LANs",
            "children": [
                {
                    "name": "bridge/switch"
                }
            ]
        },
        {
            "name": "Layer-3 Protocol based Virtual LANs",
            "children": [
                {
                    "name": "bridge/switch"
                }
            ]
        },
        {
            "name": "Distribution",
            "children": [
                {
                    "name": "VLAN"
                }
            ]
        },
        {
            "name": "Relay",
            "children": [
                {
                    "name": "tagged"
                },
                {
                    "name": "VLAN",
                    "children": [
                        {
                            "name": "explicit"
                        },
                        {
                            "name": "tagging"
                        }
                    ]
                },
                {
                    "name": "rule"
                }
            ]
        },
        {
            "name": "Frame Tagging",
            "children": [
                {
                    "name": "tagging"
                },
                {
                    "name": "explicit"
                }
            ]
        },
        {
            "name": "Port-Based VLAN Definitions",
            "children": [
                {
                    "name": "VLAN"
                },
                {
                    "name": "unaware device"
                },
                {
                    "name": "access link"
                }
            ]
        },
        {
            "name": "Definitions",
            "children": [
                {
                    "name": "VLAN",
                    "children": [
                        {
                            "name": "trunk link"
                        },
                        {
                            "name": "all frame"
                        },
                        {
                            "name": "tagged"
                        }
                    ]
                }
            ]
        },
        {
            "name": "Rules for Tagging Frames on a Hybrid link",
            "children": [
                {
                    "name": "all frame"
                },
                {
                    "name": "tagged"
                },
                {
                    "name": "explicit"
                },
                {
                    "name": "hybrid link"
                }
            ]
        },
        {
            "name": "Spanning Tree and VLAN",
            "children": [
                {
                    "name": "VLAN",
                    "children": [
                        {
                            "name": "member set"
                        }
                    ]
                }
            ]
        },
        {
            "name": "IVL Example -- Multiple Independent VLANs",
            "children": [
                {
                    "name": "connector"
                },
                {
                    "name": "VLAN"
                },
                {
                    "name": "the filtering database"
                }
            ]
        },
        {
            "name": "The Filtering Databases for VLAN",
            "children": [
                {
                    "name": "filtering entry"
                }
            ]
        },
        {
            "name": "Static VLAN Registration Entry",
            "children": [
                {
                    "name": "VLAN"
                }
            ]
        },
        {
            "name": "Dynamic VLAN Registration Entry",
            "children": [
                {
                    "name": "VLAN"
                }
            ]
        },
        {
            "name": "Summary",
            "children": [
                {
                    "name": "VLAN"
                },
                {
                    "name": "group",
                    "children": [
                        {
                            "name": "all frame"
                        },
                        {
                            "name": "tagged"
                        },
                        {
                            "name": "access link"
                        },
                        {
                            "name": "trunk link"
                        },
                        {
                            "name": "hybrid link"
                        }
                    ]
                }
            ]
        }
    ]
}